dodoenv/__init__.py
dodoenv/py.typed
dodoenv/internal/__init__.py
dodoenv/internal/env.py
dodoenv/internal/exception.py
dodoenv-0.1.0.dist-info/licenses/LICENSE
dodoenv-0.1.0.dist-info/METADATA
dodoenv-0.1.0.dist-info/WHEEL
dodoenv-0.1.0.dist-info/top_level.txt
dodoenv-0.1.0.dist-info/RECORD
